{
  "legislative_session": "24",
  "identifier": "HLB 24-1",
  "title": "To appropriate $11,877.00 for the operations of the Mayor Tinian and Aguiguan pursuant to 10 CMC \u00a7 2581 and 1 CMC \u00a7 1405.",
  "from_organization": "~{\"classification\": \"lower\"}",
  "classification": [
    "bill"
  ],
  "subject": [],
  "abstracts": [],
  "other_titles": [],
  "other_identifiers": [],
  "actions": [
    {
      "description": "Date Introduced",
      "date": "2025-02-14",
      "organization_id": "~{\"classification\": \"lower\"}",
      "classification": [
        "introduction"
      ],
      "related_entities": [],
      "_processing": {
        "log_file_created": "2025-10-25T03:00:33Z"
      }
    },
    {
      "description": "House First Reading",
      "date": "2025-02-25",
      "organization_id": "~{\"classification\": \"lower\"}",
      "classification": [
        "reading-1"
      ],
      "related_entities": [],
      "_processing": {
        "log_file_created": "2025-10-25T03:00:33Z"
      }
    },
    {
      "description": "House Final Reading",
      "date": "2025-02-25",
      "organization_id": "~{\"classification\": \"lower\"}",
      "classification": [
        "reading-2"
      ],
      "related_entities": [],
      "_processing": {
        "log_file_created": "2025-10-25T03:00:33Z"
      }
    },
    {
      "description": "T.L.L. 24-1",
      "date": "2025-02-28",
      "organization_id": "~{\"classification\": \"executive\"}",
      "classification": [
        "became-law"
      ],
      "related_entities": [],
      "_processing": {
        "log_file_created": "2025-10-25T03:00:33Z"
      }
    }
  ],
  "sponsorships": [
    {
      "name": "San Nicolas, PH",
      "classification": "primary",
      "entity_type": "person",
      "primary": true,
      "person_id": "~{\"name\": \"San Nicolas, PH\"}",
      "organization_id": null
    }
  ],
  "related_bills": [],
  "versions": [
    {
      "note": "HLB 24-1",
      "links": [
        {
          "url": "https://cnmileg.net/documents/house/hse_lb/24/HLB24-1.pdf",
          "media_type": "application/pdf"
        }
      ],
      "date": "",
      "classification": ""
    },
    {
      "note": "T.L.L. 24-1",
      "links": [
        {
          "url": "https://cnmileg.net/documents/files/23rd%20update/TLL%2024-1%20(HLB%2024-1%20D1%20To%20appropriate%20%2411%2C877%20for%20the%20personnel%20and%20operations%20of%20the%20TCGCCC%20pursuant%20to%2010%20CMC%20%C2%A7%202581%20and%201%20CMC%20%C2%A7%201405).pdf",
          "media_type": "application/pdf"
        }
      ],
      "date": "",
      "classification": ""
    }
  ],
  "documents": [],
  "citations": [],
  "sources": [
    {
      "url": "https://cnmileg.net/leg_sts.asp?legID=19801&secID=1",
      "note": ""
    }
  ],
  "extras": {},
  "jurisdiction": {
    "id": "ocd-jurisdiction/country:us/territory:mp/government",
    "name": "Northern Mariana Islands",
    "classification": "state",
    "division_id": "ocd-division/country:us/territory:mp"
  },
  "_processing": {
    "logs_latest_update": "2025-10-25T03:00:33Z",
    "text_extraction_latest_update": "2025-10-25T09:01:08.407911Z"
  }
}