{
  "legislative_session": "24",
  "identifier": "HB 24-3",
  "title": "To eliminate the 10% distribution to the Commonwealth Utilities Corporation, and redistribute those funds equally between the Bureau of Motor Vehicles and the Department of Public Works to enhance their operational capacities; and for other purposes.",
  "from_organization": "~{\"classification\": \"lower\"}",
  "classification": [
    "bill"
  ],
  "subject": [],
  "abstracts": [],
  "other_titles": [],
  "other_identifiers": [],
  "actions": [
    {
      "description": "Date Introduced",
      "date": "2025-02-14",
      "organization_id": "~{\"classification\": \"lower\"}",
      "classification": [
        "introduction"
      ],
      "related_entities": [],
      "_processing": {
        "log_file_created": "2025-10-25T03:00:33Z"
      }
    },
    {
      "description": "HOUSE-PUTC",
      "date": "2025-02-14",
      "organization_id": "~{\"classification\": \"lower\"}",
      "classification": [
        "referral-committee"
      ],
      "related_entities": [],
      "_processing": {
        "log_file_created": "2025-10-25T03:00:33Z"
      }
    }
  ],
  "sponsorships": [
    {
      "name": "Aldan, VR",
      "classification": "primary",
      "entity_type": "person",
      "primary": true,
      "person_id": "~{\"name\": \"Aldan, VR\"}",
      "organization_id": null
    }
  ],
  "related_bills": [],
  "versions": [
    {
      "note": "HB 24-3",
      "links": [
        {
          "url": "https://cnmileg.net/documents/house/hse_bills/24/HB24-3.pdf",
          "media_type": "application/pdf"
        }
      ],
      "date": "",
      "classification": ""
    }
  ],
  "documents": [],
  "citations": [],
  "sources": [
    {
      "url": "https://cnmileg.net/leg_sts.asp?legID=19813&secID=1",
      "note": ""
    }
  ],
  "extras": {},
  "jurisdiction": {
    "id": "ocd-jurisdiction/country:us/territory:mp/government",
    "name": "Northern Mariana Islands",
    "classification": "state",
    "division_id": "ocd-division/country:us/territory:mp"
  },
  "_processing": {
    "logs_latest_update": "2025-10-25T03:00:33Z",
    "text_extraction_latest_update": "2025-10-25T09:04:01.042142Z"
  }
}